draggable_charts/__init__.py
draggable_charts/example.py
draggable_charts/frontend/build/asset-manifest.json
draggable_charts/frontend/build/bootstrap.min.css
draggable_charts/frontend/build/index.html
draggable_charts/frontend/build/static/js/main.f3ea7fdc.js
draggable_charts/frontend/build/static/js/main.f3ea7fdc.js.LICENSE.txt
draggable_charts/frontend/build/static/js/main.f3ea7fdc.js.map
draggable_charts/utils/__init__.py
draggable_charts/utils/component_func.py
draggable_charts/widgets/__init__.py
draggable_charts/widgets/bezierchart.py
draggable_charts/widgets/linechart.py
draggable_charts/widgets/scatterchart.py
draggable_line_chart/__init__.py
draggable_line_chart/example.py
draggable_line_chart/frontend/build/asset-manifest.json
draggable_line_chart/frontend/build/bootstrap.min.css
draggable_line_chart/frontend/build/index.html
draggable_line_chart/frontend/build/static/js/main.7210bbf2.js
draggable_line_chart/frontend/build/static/js/main.7210bbf2.js.LICENSE.txt
draggable_line_chart/frontend/build/static/js/main.7210bbf2.js.map
draggable_line_chart/frontend/build/static/js/main.ba7d93c8.js
draggable_line_chart/frontend/build/static/js/main.ba7d93c8.js.LICENSE.txt
draggable_line_chart/frontend/build/static/js/main.ba7d93c8.js.map
draggable_line_chart/frontend/build/static/js/main.c8906afb.js
draggable_line_chart/frontend/build/static/js/main.c8906afb.js.LICENSE.txt
draggable_line_chart/frontend/build/static/js/main.c8906afb.js.map
draggable_line_chart/frontend/build/static/js/main.ce187111.js
draggable_line_chart/frontend/build/static/js/main.ce187111.js.LICENSE.txt
draggable_line_chart/frontend/build/static/js/main.ce187111.js.map
draggable_line_chart/frontend/build/static/js/main.ced5ae94.js
draggable_line_chart/frontend/build/static/js/main.ced5ae94.js.LICENSE.txt
draggable_line_chart/frontend/build/static/js/main.ced5ae94.js.map
draggable_line_chart-1.0.0.dist-info/LICENSE
draggable_line_chart-1.0.0.dist-info/METADATA
draggable_line_chart-1.0.0.dist-info/WHEEL
draggable_line_chart-1.0.0.dist-info/top_level.txt
draggable_line_chart-1.0.0.dist-info/RECORD
