Metadata-Version: 2.1
Name: draggable-line-chart
Version: 1.0.0
Summary: A Streamlit component that displays a line chart with draggable points. Users can click and drag points on the chart to adjust their values. The updated data of the chart is returned.
Home-page: https://github.com/balexandermunoz/draggable-charts
Author: Brayan Munoz
Author-email: balexander.munoz@udea.edu.co
Requires-Python: >=3.7
License-File: LICENSE
Requires-Dist: streamlit >=0.63
Provides-Extra: devel
Requires-Dist: wheel ; extra == 'devel'
Requires-Dist: pytest ==7.4.0 ; extra == 'devel'
Requires-Dist: playwright ==1.39.0 ; extra == 'devel'
Requires-Dist: requests ==2.31.0 ; extra == 'devel'
Requires-Dist: pytest-playwright-snapshot ==1.0 ; extra == 'devel'
Requires-Dist: pytest-rerunfailures ==12.0 ; extra == 'devel'
